README.md
setup.py
Ranthon.egg-info/PKG-INFO
Ranthon.egg-info/SOURCES.txt
Ranthon.egg-info/dependency_links.txt
Ranthon.egg-info/top_level.txt
infseq/__init__.py
infseq/fibseq.py