Metadata-Version: 2.1
Name: Ranthon
Version: 1.0.2
Summary: A collection of Python packages written by Walter J Hare.
Home-page: UNKNOWN
License: UNKNOWN
Platform: UNKNOWN
Requires: filelog
